spectracles/__init__.py
spectracles/_version.py
spectracles/py.typed
spectracles/model/__init__.py
spectracles/model/data.py
spectracles/model/graph.py
spectracles/model/io.py
spectracles/model/kernels.py
spectracles/model/parameter.py
spectracles/model/share_module.py
spectracles/model/spatial.py
spectracles/model/spectral.py
spectracles/optimise/__init__.py
spectracles/optimise/opt_frame.py
spectracles/optimise/opt_schedule.py
spectracles/tree/__init__.py
spectracles/tree/path_utils.py
spectracles-0.5.4.dist-info/METADATA
spectracles-0.5.4.dist-info/WHEEL
spectracles-0.5.4.dist-info/licenses/LICENSE
spectracles-0.5.4.dist-info/RECORD
