Metadata-Version: 2.4
Name: spectracles
Version: 0.5.4
Summary: Unified spectrospatial models: glasses for your spectra.
Author-email: Thomas Hilder <Thomas.Hilder@monash.edu>, "Andrew R. Casey" <Andrew.Casey@monash.edu>
License-File: LICENSE
Requires-Python: >=3.13
Requires-Dist: equinox>=0.13.0
Requires-Dist: jax-finufft
Requires-Dist: jax>=0.5.3
Requires-Dist: matplotlib>=3.10.5
Requires-Dist: networkx>=3.5
Requires-Dist: tqdm>=4.67.1
